{"cameraMode":{"drawMode":0,"name":"Shaded","section":"Shading Mode"},"sceneLighting":true,"audioPlay":false,"sceneViewState":{"m_AlwaysRefresh":false,"showFog":true,"showSkybox":true,"showFlares":true,"showImageEffects":true,"showParticleSystems":true,"showVisualEffectGraphs":true,"m_FxEnabled":true},"in2DMode":false,"pivot":{"x":29.57427978515625,"y":1.9194382429122925,"z":-6.709101676940918},"rotation":{"x":-0.13171882927417756,"y":0.8644247651100159,"z":-0.2963862419128418,"w":-0.3841622471809387},"size":0.7084518074989319,"orthographic":false}